codebase_to_jsonl/__init__.py
projectcodebasetojsonl-2025.5.181247.dist-info/licenses/LICENSE
projectcodebasetojsonl-2025.5.181247.dist-info/METADATA
projectcodebasetojsonl-2025.5.181247.dist-info/WHEEL
projectcodebasetojsonl-2025.5.181247.dist-info/top_level.txt
projectcodebasetojsonl-2025.5.181247.dist-info/RECORD
