Metadata-Version: 2.4
Name: ProjectCodebaseToJsonl
Version: 2025.5.181247
Summary: A package to convert project codebases into JSONL format for GPT model training.
Home-page: https://github.com/chigwell/ProjectCodebaseToJsonl
Author: Eugene Evstafev
Author-email: chigwel@gmail.com
Classifier: Programming Language :: Python :: 3
Classifier: License :: OSI Approved :: MIT License
Classifier: Operating System :: OS Independent
Requires-Python: >=3.6
License-File: LICENSE
Requires-Dist: pathspec
Dynamic: author
Dynamic: author-email
Dynamic: classifier
Dynamic: description
Dynamic: description-content-type
Dynamic: home-page
Dynamic: license-file
Dynamic: requires-dist
Dynamic: requires-python
Dynamic: summary
